ethicalzen/__init__.py
ethicalzen/client.py
ethicalzen/exceptions.py
ethicalzen/models.py
ethicalzen/proxy.py
ethicalzen-0.1.1.dist-info/METADATA
ethicalzen-0.1.1.dist-info/WHEEL
ethicalzen-0.1.1.dist-info/RECORD
