Metadata-Version: 2.4
Name: ethicalzen
Version: 0.1.1
Summary: Python SDK for EthicalZen AI Guardrails - Runtime enforcement for AI compliance
Project-URL: Homepage, https://ethicalzen.ai
Project-URL: Documentation, https://ethicalzen.ai/docs
Project-URL: Repository, https://github.com/aiworksllc/ethicalzen-accelerators
Project-URL: Issues, https://github.com/aiworksllc/ethicalzen-accelerators/issues
Author-email: EthicalZen <support@ethicalzen.ai>
License-Expression: Apache-2.0
Keywords: ai,compliance,ethicalzen,guardrails,llm,moderation,safety
Classifier: Development Status :: 4 - Beta
Classifier: Intended Audience :: Developers
Classifier: License :: OSI Approved :: Apache Software License
Classifier: Operating System :: OS Independent
Classifier: Programming Language :: Python :: 3
Classifier: Programming Language :: Python :: 3.8
Classifier: Programming Language :: Python :: 3.9
Classifier: Programming Language :: Python :: 3.10
Classifier: Programming Language :: Python :: 3.11
Classifier: Programming Language :: Python :: 3.12
Classifier: Topic :: Scientific/Engineering :: Artificial Intelligence
Classifier: Topic :: Security
Requires-Python: >=3.8
Requires-Dist: httpx>=0.24.0
Requires-Dist: pydantic>=2.0.0
Provides-Extra: dev
Requires-Dist: black>=23.0.0; extra == 'dev'
Requires-Dist: mypy>=1.0.0; extra == 'dev'
Requires-Dist: pytest-asyncio>=0.21.0; extra == 'dev'
Requires-Dist: pytest-cov>=4.0.0; extra == 'dev'
Requires-Dist: pytest>=7.0.0; extra == 'dev'
Requires-Dist: ruff>=0.1.0; extra == 'dev'
